convert_images/.DS_Store
convert_images/__init__.py
convert_images/convert_images.py
convert_images-0.1.0.dist-info/entry_points.txt
convert_images-0.1.0.dist-info/WHEEL
convert_images-0.1.0.dist-info/METADATA
convert_images-0.1.0.dist-info/RECORD
