Metadata-Version: 2.1
Name: convert-images
Version: 0.1.0
Summary: Simple CLI to convert images to JPEG and PNG format
License: MIT
Author: Mohammad Alyetama
Author-email: malyetama@pm.me
Requires-Python: >=3.6,<4.0
Classifier: License :: OSI Approved :: MIT License
Classifier: Programming Language :: Python :: 3
Classifier: Programming Language :: Python :: 3.10
Classifier: Programming Language :: Python :: 3.6
Classifier: Programming Language :: Python :: 3.7
Classifier: Programming Language :: Python :: 3.8
Classifier: Programming Language :: Python :: 3.9
Requires-Dist: Pillow (>7)
Requires-Dist: loguru (>=0.6.0,<0.7.0)
